first_trial/first_trial.v
// first_trial.v
module first_trial(
    input wire clk,
    input wire rst,
    output reg y,
    output reg [31:0] count
);

localparam IDLE = 3'b000;
localparam SUM = 3'b001;
localparam MULT = 3'b010;
localparam DIV = 3'b011;
localparam EXT = 3'b100;

reg a = 1;
reg b = 1;

reg [2:0]curr_state;
reg [2:0]next_state;
reg [31:0]firstArr = 32'h00000002;
reg [31:0]secondArr = 32'h00000003;
reg [31:0]thirdArr = 32'h00000000;
reg [31:0]fourthArr = 32'h00000000;
reg [31:0]result1Arr = 32'h00000000;
reg [31:0]result2Arr = 32'h00000000;

always @(*) begin
    y = a & b;
end
 
// first process
always @(posedge clk or posedge rst) begin

    if (rst) begin
        curr_state <= IDLE;  // asynchronous reset
        count <= 0;
        firstArr <= 32'h00000002;
        result1Arr <= 32'h00000003;
    end
    else begin
        case(curr_state)
            IDLE: begin
                firstArr <= 32'h00000002;
                result1Arr <= 32'h00000003;
                count <= result1Arr;
                curr_state <= SUM;
            end 
            SUM: begin
                result1Arr <= firstArr + result1Arr;
                curr_state <= MULT;
                b <= 0;
            end
            MULT: begin
                result1Arr <= firstArr * result1Arr;
                firstArr <= firstArr + 2'b11;
                a <= 0;
                curr_state <= DIV;
            end
            DIV: begin
                result1Arr <= result1Arr / firstArr;
                a <= 1;
                b <= 1;
                curr_state <= EXT;
            end
            EXT: begin
                result1Arr <= firstArr - result1Arr;
                curr_state <= IDLE;
            end
            default: begin
                curr_state <= IDLE;
            end
        endcase
    end

end
// second process
always @(posedge clk or posedge rst) begin
 if (rst) begin
        next_state <= IDLE;  // asynchronous reset
        thirdArr <= 32'h3;
        fourthArr <= 32'h4;
        result2Arr <= 32'h5;
    end
    else begin
        case(next_state)
            IDLE: begin
                thirdArr <= 32'h3;
                fourthArr <= 32'h4;
                result2Arr <= 32'h5;
                next_state <= SUM;
            end 
            SUM: begin
                thirdArr <= 32'h6;
                fourthArr <= 32'h7;
                result2Arr <= 32'h8;
                next_state <= MULT;
            end 
            MULT: begin
                thirdArr <= 32'h9;
                fourthArr <= 32'ha;
                result2Arr <= 32'hb;
                next_state <= DIV;
            end
            DIV: begin
                thirdArr <= 32'hc;
                fourthArr <= 32'hd;
                result2Arr <= 32'he;
                next_state <= EXT;
            end
            EXT: begin
                thirdArr <= 32'hf;
                fourthArr <= 32'h10;
                result2Arr <= 32'h11;
                next_state <= IDLE;
            end
            default: begin
                next_state <= IDLE;
            end
        endcase
    end
end

endmodule

first_trial/tb_first_trial.v
// tb_first_trial.v
`timescale 1ns/1ps

module tb_first_trial;
reg clk;
reg rst;
wire y;
wire [31:0] count;


first_trial uut (
    .clk(clk),
    .rst(rst),
    .y(y),
    .count(count)
);

// Clock generation (10ns period)
always #5 clk = ~clk;

initial begin
    // Init signals
    clk = 0;
    rst = 1;
    #10;
    rst = 0;

    // Run for 200ns then stop
    #200;
    $finish;
end

// Dump waveform
initial begin
    $dumpfile("wave.vcd");
    $dumpvars(0, tb_first_trial);
end

endmodule

first_trial/wave.vcd
$date
	Sat Aug 30 21:13:35 2025
$end
$version
	Icarus Verilog
$end
$timescale
	1ps
$end
$scope module tb_first_trial $end
$var wire 1 ! y $end
$var wire 32 " count [31:0] $end
$var reg 1 # clk $end
$var reg 1 $ rst $end
$scope module uut $end
$var wire 1 # clk $end
$var wire 1 $ rst $end
$var parameter 3 % DIV $end
$var parameter 3 & EXT $end
$var parameter 3 ' IDLE $end
$var parameter 3 ( MULT $end
$var parameter 3 ) SUM $end
$var reg 1 * a $end
$var reg 1 + b $end
$var reg 32 , count [31:0] $end
$var reg 3 - curr_state [2:0] $end
$var reg 32 . firstArr [31:0] $end
$var reg 32 / fourthArr [31:0] $end
$var reg 3 0 next_state [2:0] $end
$var reg 32 1 result1Arr [31:0] $end
$var reg 32 2 result2Arr [31:0] $end
$var reg 32 3 secondArr [31:0] $end
$var reg 32 4 thirdArr [31:0] $end
$var reg 1 ! y $end
$upscope $end
$upscope $end
$enddefinitions $end
$comment Show the parameter values. $end
$dumpall
b1 )
b10 (
b0 '
b100 &
b11 %
$end
#0
$dumpvars
b11 4
b11 3
b101 2
b11 1
b0 0
b100 /
b10 .
b0 -
b0 ,
1+
1*
1$
0#
b0 "
1!
$end
#5000
1#
#10000
0#
0$
#15000
b1 -
b11 "
b11 ,
b1 0
1#
#20000
0#
#25000
0!
b10 0
b1000 2
b111 /
b110 4
0+
b10 -
b101 1
1#
#30000
0#
#35000
b11 -
0*
b101 .
b1010 1
b11 0
b1011 2
b1010 /
b1001 4
1#
#40000
0#
#45000
1!
b100 0
b1110 2
b1101 /
b1100 4
b100 -
1+
1*
b10 1
1#
#50000
0#
#55000
b0 -
b10 "
b10 ,
b11 1
b0 0
b10001 2
b10000 /
b1111 4
1#
#60000
0#
#65000
b1 0
b101 2
b100 /
b11 4
b1 -
b11 "
b11 ,
b10 .
1#
#70000
0#
#75000
0!
0+
b10 -
b101 1
b10 0
b1000 2
b111 /
b110 4
1#
#80000
0#
#85000
b11 0
b1011 2
b1010 /
b1001 4
b11 -
0*
b101 .
b1010 1
1#
#90000
0#
#95000
1!
b100 -
1+
1*
b10 1
b100 0
b1110 2
b1101 /
b1100 4
1#
#100000
0#
#105000
b0 0
b10001 2
b10000 /
b1111 4
b0 -
b10 "
b10 ,
b11 1
1#
#110000
0#
#115000
b1 -
b11 "
b11 ,
b10 .
b1 0
b101 2
b100 /
b11 4
1#
#120000
0#
#125000
0!
b10 0
b1000 2
b111 /
b110 4
0+
b10 -
b101 1
1#
#130000
0#
#135000
b11 -
0*
b101 .
b1010 1
b11 0
b1011 2
b1010 /
b1001 4
1#
#140000
0#
#145000
1!
b100 0
b1110 2
b1101 /
b1100 4
b100 -
1+
1*
b10 1
1#
#150000
0#
#155000
b0 -
b10 "
b10 ,
b11 1
b0 0
b10001 2
b10000 /
b1111 4
1#
#160000
0#
#165000
b1 0
b101 2
b100 /
b11 4
b1 -
b11 "
b11 ,
b10 .
1#
#170000
0#
#175000
0!
0+
b10 -
b101 1
b10 0
b1000 2
b111 /
b110 4
1#
#180000
0#
#185000
b11 0
b1011 2
b1010 /
b1001 4
b11 -
0*
b101 .
b1010 1
1#
#190000
0#
#195000
1!
b100 -
1+
1*
b10 1
b100 0
b1110 2
b1101 /
b1100 4
1#
#200000
0#
#205000
b0 0
b10001 2
b10000 /
b1111 4
b0 -
b10 "
b10 ,
b11 1
1#
